{
    "考研题目": [
        {
            "问题": "1、Python源程序执行的方式是什么？",
            "选项": [
                "A、编译执行",
                "B、解析执行",
                "C、直接执行",
                "D、边编译边执行"
            ],
            "答案": "B、解析执行",
            "错误次数": 0,
            "最近错过": 0,
            "题目出现次数": 0
        },
        {
            "问题": "2、以下哪个不是Python中的关键字？",
            "选项": [
                "A、raise",
                "B、with",
                "C、import",
                "D、final"
            ],
            "答案": "D、final",
            "错误次数": 9,
            "最近错过": 0,
            "题目出现次数": 0
        },
        {
            "问题": "3、下面哪个不是Python合法的标识符？",
            "选项": [
                "A、int32",
                "B、40XL",
                "C、self",
                "D、name"
            ],
            "答案": "B、40XL",
            "错误次数": 1,
            "最近错过": 0,
            "题目出现次数": 0
        },
        {
            "问题": "4、以下哪个类型不可以进行切片操作？",
            "选项": [
                "A、str",
                "B、list",
                "C、tuple",
                "D、dict"
            ],
            "答案": "D、dict",
            "错误次数": 2,
            "最近错过": 0,
            "题目出现次数": 0
        },
        {
            "问题": "5、命题是可以判断真假是的什么句？",
            "选项": [
                "A、陈述句",
                "B、疑问句",
                "C、感叹句",
                "D、祈使句"
            ],
            "答案": "A、陈述句",
            "错误次数": 6,
            "最近错过": 1,
            "题目出现次数": 0
        },
        {
            "问题": "6、1997年5月，著名的“人机大战”，最终计算机以3.5比2.5的总比分将世界国际象棋棋王卡斯帕罗夫击败，这台计算机被称为",
            "选项": [
                "A、IBM",
                "B、深思",
                "C、深蓝",
                "D、蓝天"
            ],
            "答案": "C、深蓝",
            "错误次数": 7,
            "最近错过": 2,
            "题目出现次数": 0
        },
        {
            "问题": "7、不属于人工智能学派的是？",
            "选项": [
                "A、机会主义",
                "B、符号主义",
                "C、连接主义",
                "D、行为主义"
            ],
            "答案": "A、机会主义",
            "错误次数": 1,
            "最近错过": 0,
            "题目出现次数": 0
        },
        {
            "问题": "8、曲线`y=(x^2+x)/(x^2-1)`有多少条渐近线？",
            "选项": [
                "A、0",
                "B、1",
                "C、2",
                "D、3"
            ],
            "答案": "C、2",
            "错误次数": 4,
            "最近错过": 1,
            "题目出现次数": 0
        },
        {
            "问题": "9、设区域D由曲线`y=sinx,x=±π/2,y=1`围成,则`\\int\\int(xy^2-1)dxdy=`",
            "选项": [
                "A、π",
                "B、2",
                "C、-2",
                "D、-π"
            ],
            "答案": "D、-π",
            "错误次数": 0,
            "最近错过": 0,
            "题目出现次数": 0
        },
        {
            "问题": "10、`\\int_0^1 x^2 dx`为_____。",
            "选项": [
                "A、π",
                "B、2",
                "C、-2",
                "D、-π"
            ],
            "答案": "D、-π",
            "错误次数": 3,
            "最近错过": 1,
            "题目出现次数": 0
        }
    ]
}